{"updated":"2019-08-29T11:44:29-07:00","validated_snapshot_id":565,"editorial_layout_id":53,"sections":[{"ordinal":0,"format":"small_grid","description":"","ios_color":"#3C3C3C","tvos_light_style_color":"#3C3C3C","tvos_dark_style_color":"#6B6B6B","title":"What’s New","image_type":"wide","content":[{"ordinal":0,"identifier":"tech-talks-608"},{"ordinal":1,"identifier":"tech-talks-301"},{"ordinal":2,"identifier":"tech-talks-210"}]},{"ordinal":1,"format":"small_grid","description":"","ios_color":"#3C3C3C","tvos_light_style_color":"#3C3C3C","tvos_dark_style_color":"#6B6B6B","title":"Apps for Everyone","image_type":"wide","content":[{"ordinal":0,"identifier":"wwdc2019-254"},{"ordinal":1,"identifier":"wwdc2019-244"},{"ordinal":2,"identifier":"wwdc2019-248"},{"ordinal":3,"identifier":"wwdc2019-261"},{"ordinal":4,"identifier":"wwdc2018-241"},{"ordinal":5,"identifier":"wwdc2017-217"}]},{"ordinal":2,"format":"small_grid","description":"","ios_color":"#3C3C3C","tvos_light_style_color":"#3C3C3C","tvos_dark_style_color":"#6B6B6B","title":"Moving with Apple Watch","image_type":"wide","content":[{"ordinal":0,"identifier":"wwdc2019-219"},{"ordinal":1,"identifier":"wwdc2017-713"},{"ordinal":2,"identifier":"wwdc2019-426"},{"ordinal":3,"identifier":"wwdc2016-713"}]},{"ordinal":3,"format":"small_grid","description":"","ios_color":"#3C3C3C","tvos_light_style_color":"#3C3C3C","tvos_dark_style_color":"#6B6B6B","title":"Flexible UI","image_type":"wide","content":[{"ordinal":0,"identifier":"wwdc2019-224"},{"ordinal":1,"identifier":"wwdc2017-204"},{"ordinal":2,"identifier":"tech-talks-201"},{"ordinal":3,"identifier":"tech-talks-207"},{"ordinal":4,"identifier":"tech-talks-209"}]}]}